planfftw/__init__.py
planfftw/_numpy_basics.py
planfftw/_pyfftw_basics.py
planfftw/_scipy_basics.py
planfftw/_utils.py
planfftw/planners.py
planfftw-1.2.0.dist-info/LICENSE.txt
planfftw-1.2.0.dist-info/METADATA
planfftw-1.2.0.dist-info/WHEEL
planfftw-1.2.0.dist-info/top_level.txt
planfftw-1.2.0.dist-info/RECORD
